aioqs.py
aioqs-0.6.dist-info/LICENSE
aioqs-0.6.dist-info/METADATA
aioqs-0.6.dist-info/WHEEL
aioqs-0.6.dist-info/top_level.txt
aioqs-0.6.dist-info/RECORD
