Metadata-Version: 2.1
Name: aioqs
Version: 0.6
Summary: Async queue and scheduler with limit for number of simultaneous coroutines
Home-page: https://github.com/wWolfovich/aioqs
Author: Oleg Marin
Author-email: wWolfovich@gmail.com
License: UNKNOWN
Keywords: AIO async queue schedule
Platform: UNKNOWN
Classifier: Programming Language :: Python :: 3
Classifier: License :: OSI Approved :: GNU Affero General Public License v3 or later (AGPLv3+)
Classifier: Operating System :: OS Independent
Requires-Python: >=3.5.2
Provides-Extra: async_timeout
Requires-Dist: async-timeout ; extra == 'async_timeout'
